exedash/__init__.py
exedash/core.py
exedash-1.0.1.dist-info/licenses/LICENSE
exedash-1.0.1.dist-info/METADATA
exedash-1.0.1.dist-info/WHEEL
exedash-1.0.1.dist-info/top_level.txt
exedash-1.0.1.dist-info/RECORD
